Workbook
Name aporte_mes: FIIs!$K$9
Name dividendo_mes: FIIs!$K$13
Name patrimonio: FIIs!$K$12
Name salario: FIIs!$K$5
Name tempo_ano: FIIs!$K$10
Name tx_anual: FIIs!$M$9
Name tx_mensal: FIIs!$K$11
Name tx_selic: FIIs!$M$5

Sheet FIIs
B2: FUNDOS IMOBILIÁRIOS
B4: CONFIGURAÇÕES | M4: Taxa Selic (a.a)
B5: Salário Líquido | K5: 5000 | M5: 0.15
B6: Sugestão de aporte | K6: =$K$5*30% -> 1500
B8: PROJEÇÕES DE INVESTIMENTOS | M8: Rendimento (a.a)
B9: Aportes mensais | K9: 500 | M9: =(1+$K$11)^12-1 -> 0.12682503
B10: Tempo de Investimento (Anos) | K10: 5
B11: Taxa Mensal | K11: 0.01
B12: Patrimônio Acumulado | K12: =FV($K$11,$K$10*12,K9*-1) -> 40834.835
B13: Dividendos Mensais | K13: =K12*K11 -> 408.34835
B15: PROJEÇÕES DE INVESTIMENTOS | J15: PATRIMONIO | K15: DIVIDENDOS
A16: 5 | B16: 5 anos | J16: =FV(tx_mensal,$A16*12,aporte_mes*-1) -> 40834.835 | K16: =J16*tx_mensal -> 408.34835
A17: 10 | B17: 10 anos | J17: =FV(tx_mensal,$A17*12,aporte_mes*-1) -> 115019.34 | K17: =J17*tx_mensal -> 1150.1934
A18: 15 | B18: 15 anos | J18: =FV(tx_mensal,$A18*12,aporte_mes*-1) -> 249790.1 | K18: =J18*tx_mensal -> 2497.901
A19: 20 | B19: 20 anos | J19: =FV(tx_mensal,$A19*12,aporte_mes*-1) -> 494627.68 | K19: =J19*tx_mensal -> 4946.2768
B21: PERFIL DE INVESTIDOR
B22: Aportes mensais | K22: =aporte_mes -> 500
B23: Perfil | K23: Conservador
B25: TIPO DE FII | J25: PERCENTUAL | K25: VALOR
B26: PAPEL | J26: =VLOOKUP($K$23&"-"&B26,aux!A2:C22,3,0) -> 0.15 | K26: =J26*$K$22 -> 75
B27: SHOPPING | J27: =VLOOKUP($K$23&"-"&B27,aux!A3:C23,3,0) -> 0.25 | K27: =J27*$K$22 -> 125
B28: LOGISTICA | J28: =VLOOKUP($K$23&"-"&B28,aux!A4:C24,3,0) -> 0.25 | K28: =J28*$K$22 -> 125
B29: LAJES CORPORATIVAS | J29: =VLOOKUP($K$23&"-"&B29,aux!A5:C25,3,0) -> 0.25 | K29: =J29*$K$22 -> 125
B30: DESENVOLVIMENTO | J30: =VLOOKUP($K$23&"-"&B30,aux!A6:C26,3,0) -> 0 | K30: =J30*$K$22 -> 0
B31: MULTIESTRATÉGIA | J31: =VLOOKUP($K$23&"-"&B31,aux!A7:C27,3,0) -> 0.05 | K31: =J31*$K$22 -> 25
B32: RENDA URBANA | J32: =VLOOKUP($K$23&"-"&B32,aux!A8:C28,3,0) -> 0.05 | K32: =J32*$K$22 -> 25
K33: =SUM(K26:K32) -> 500

Sheet aux
A1: Perfil | B1: Segmentos | C1: Porcentagem
A2: Conservador-PAPEL | B2: PAPEL | C2: 0.15 | E2: =A2&"-"&B2 -> Conservador-PAPEL-PAPEL
A3: Conservador-SHOPPING | B3: SHOPPING | C3: 0.25 | E3: =A3&"-"&B3 -> Conservador-SHOPPING-SHOPPING
A4: Conservador-LOGISTICA | B4: LOGISTICA | C4: 0.25 | E4: =A4&"-"&B4 -> Conservador-LOGISTICA-LOGISTICA
A5: Conservador-LAJES CORPORATIVAS | B5: LAJES CORPORATIVAS | C5: 0.25 | E5: =A5&"-"&B5 -> Conservador-LAJES CORPORATIVAS-LAJES CORPORATIVAS
A6: Conservador-DESENVOLVIMENTO | B6: DESENVOLVIMENTO | C6: 0 | E6: =A6&"-"&B6 -> Conservador-DESENVOLVIMENTO-DESENVOLVIMENTO
A7: Conservador-MULTIESTRATÉGIA | B7: MULTIESTRATÉGIA | C7: 0.05 | E7: =A7&"-"&B7 -> Conservador-MULTIESTRATÉGIA-MULTIESTRATÉGIA
A8: Conservador-RENDA URBANA | B8: RENDA URBANA | C8: 0.05 | E8: =A8&"-"&B8 -> Conservador-RENDA URBANA-RENDA URBANA
A9: Moderado-PAPEL | B9: PAPEL | C9: 0.2 | E9: =A9&"-"&B9 -> Moderado-PAPEL-PAPEL
A10: Moderado-SHOPPING | B10: SHOPPING | C10: 0.17 | E10: =A10&"-"&B10 -> Moderado-SHOPPING-SHOPPING
A11: Moderado-LOGISTICA | B11: LOGISTICA | C11: 0.17 | E11: =A11&"-"&B11 -> Moderado-LOGISTICA-LOGISTICA
A12: Moderado-LAJES CORPORATIVAS | B12: LAJES CORPORATIVAS | C12: 0.17 | E12: =A12&"-"&B12 -> Moderado-LAJES CORPORATIVAS-LAJES CORPORATIVAS
A13: Moderado-DESENVOLVIMENTO | B13: DESENVOLVIMENTO | C13: 0.05 | E13: =A13&"-"&B13 -> Moderado-DESENVOLVIMENTO-DESENVOLVIMENTO
... A22: Agressivo-RENDA URBANA | B22: RENDA URBANA | C22: 0.05 | E22: =A22&"-"&B22 -> Agressivo-RENDA URBANA-RENDA URBANA
